MCRT/__init__.py
MCRT/config.py
MCRT/run.py
MCRT/assets/__init__.py
MCRT/assets/colors.py
MCRT/data_processor/__init__.py
MCRT/data_processor/cif_to_dataset.py
MCRT/data_processor/cif_to_image.py
MCRT/data_processor/dataset.py
MCRT/data_processor/split_dataset.py
MCRT/models/__init__.py
MCRT/modules/McrtModule.py
MCRT/modules/McrtTransformer.py
MCRT/modules/__init__.py
MCRT/modules/alignn.py
MCRT/modules/cgcnn.py
MCRT/modules/datamodule.py
MCRT/modules/heads.py
MCRT/modules/metrics.py
MCRT/modules/objectives.py
MCRT/modules/projector.py
MCRT/modules/utils.py
MCRT/visualize/__init__.py
MCRT/visualize/drawer.py
MCRT/visualize/setting.py
MCRT/visualize/utils.py
MCRT/visualize/visualizer.py
MCRT_tools-1.0.2.dist-info/LICENSE
MCRT_tools-1.0.2.dist-info/METADATA
MCRT_tools-1.0.2.dist-info/WHEEL
MCRT_tools-1.0.2.dist-info/top_level.txt
MCRT_tools-1.0.2.dist-info/RECORD
