Metadata-Version: 2.1
Name: MCRT-tools
Version: 1.0.2
Summary: Molecular Crystal Representation from Transformer
Home-page: https://github.com/fmggggg/MCRT
Author: Minggao Feng
Author-email: ffmmgg@liverpool.ac.uk
Classifier: Programming Language :: Python :: 3
Classifier: License :: OSI Approved :: MIT License
Classifier: Operating System :: OS Independent
Requires-Python: >=3.8
License-File: LICENSE
